hatter/__init__.py
hatter/amqp.py
hatter/domain.py
hatter/hatter.py
hatter/util.py
hatter-0.6.1.dist-info/WHEEL
hatter-0.6.1.dist-info/METADATA
hatter-0.6.1.dist-info/RECORD
