Metadata-Version: 2.1
Name: hatter
Version: 0.6.1
Summary: Framework to easily create microservices backed by a RabbitMQ broker
Home-page: https://github.com/tangibleintelligence/hatter
License: MIT
Keywords: RabbitMQ,Message Broker,Distributed Computing
Author: Austin Howard
Author-email: austin@tangibleintelligence.com
Requires-Python: >=3.8,<4.0
Classifier: Development Status :: 4 - Beta
Classifier: License :: OSI Approved :: MIT License
Classifier: Programming Language :: Python :: 3
Classifier: Programming Language :: Python :: 3.10
Classifier: Programming Language :: Python :: 3.8
Classifier: Programming Language :: Python :: 3.9
Requires-Dist: aio-pika (>=8.0.3,<9.0.0)
Requires-Dist: clearcut (>=0.2.2.post0,<0.3.0)
Requires-Dist: pydantic (>=1.8.2,<2.0.0)
Project-URL: Repository, https://github.com/tangibleintelligence/hatter
